cooppush/__init__.py
cooppush/cooppush_cpp.cpython-311-i386-linux-gnu.so
cooppush/environment.py
cooppush-1.1.9.dist-info/METADATA
cooppush-1.1.9.dist-info/top_level.txt
cooppush-1.1.9.dist-info/WHEEL
cooppush-1.1.9.dist-info/RECORD
cooppush-1.1.9.dist-info/licenses/LICENSE
