Metadata-Version: 2.4
Name: cooppush
Version: 1.1.9
Summary: MPE inspired push environment with tunable inter-action dependence for coop MARL
Author-email: Timothy Flavin <timothy.c.flavin@gmail.com>
Project-URL: Homepage, https://github.com/Timothy-Flavin/CoopPush/
Project-URL: Bug Tracker, https://github.com/Timothy-Flavin/CoopPush/issues
Classifier: Programming Language :: Python :: 3
Classifier: License :: OSI Approved :: GNU General Public License v3 (GPLv3)
Classifier: Operating System :: OS Independent
Requires-Python: >=3.11
License-File: LICENSE
Dynamic: license-file
